aa_theme_console/__init__.py
aa_theme_console/apps.py
aa_theme_console/images/aa-theme-console.jpg
aa_theme_console/static/aa_theme_console/css/aa-theme-console.css
aa_theme_console/static/aa_theme_console/css/aa-theme-console.min.css
aa_theme_console/templates/allianceauth/base.html
aa_theme_console/templates/corpstat/corpstats.html
aa_theme_console-1.5.0.dist-info/LICENSE
aa_theme_console-1.5.0.dist-info/METADATA
aa_theme_console-1.5.0.dist-info/WHEEL
aa_theme_console-1.5.0.dist-info/top_level.txt
aa_theme_console-1.5.0.dist-info/RECORD
