Metadata-Version: 2.1
Name: aa-theme-console
Version: 1.5.0
Summary: Console like Theme for Alliance Auth
Home-page: https://github.com/ppfeufer/aa-theme-console
Author: Peter Pfeufer
Author-email: develop@ppfeufer.de
Maintainer: Peter Pfeufer
Maintainer-email: develop@ppfeufer.de
License: GPL-3.0
Project-URL: Issue / Bug Reports, https://github.com/ppfeufer/aa-theme-console/issues
Project-URL: Changelog, https://github.com/ppfeufer/aa-theme-console/blob/master/CHANGELOG.md
Keywords: allianceauth,eveonline,theme,template
Classifier: Environment :: Web Environment
Classifier: Framework :: Django
Classifier: Framework :: Django :: 3.2
Classifier: Framework :: Django :: 4.0
Classifier: Intended Audience :: Developers
Classifier: License :: OSI Approved :: GNU General Public License v3 (GPLv3)
Classifier: Operating System :: OS Independent
Classifier: Programming Language :: Python
Classifier: Programming Language :: Python :: 3
Classifier: Programming Language :: Python :: 3.7
Classifier: Programming Language :: Python :: 3.8
Classifier: Programming Language :: Python :: 3.9
Classifier: Programming Language :: Python :: 3.10
Classifier: Programming Language :: Python :: 3.11
Classifier: Topic :: Internet :: WWW/HTTP
Classifier: Topic :: Internet :: WWW/HTTP :: Dynamic Content
Requires-Python: ~=3.7
License-File: LICENSE
Requires-Dist: allianceauth (>=2.14.0)
